README.md
VERSION
build.py
fling_hub/__init__.py
fling_hub/flingroute.py
fling_hub/hub.plist.template
fling_hub/loophost
fling_hub/loophost.plist.template
fling_hub/postinstall.py
fling_hub/static/fling-logo-dark.png
fling_hub/static/fling-logo-light.png
fling_hub/static/logo-hc.txt
fling_hub/templates/admin.html
fling_hub/templates/local.html
fling_hub/templates/partials/apptable.html
fling_hub/templates/partials/upgrade.html
setup.py
fling_hub-0.1.7.dist-info/METADATA
fling_hub-0.1.7.dist-info/WHEEL
fling_hub-0.1.7.dist-info/RECORD
